{
  "trade_id": "47631422-ceb9-4e36-bfa0-aff416e8f962",
  "order_link_id": "47631422-ceb9-4e36-bfa0-aff416e8f962",
  "symbol": "WOOUSDT",
  "signal_type": "long",
  "lifecycle_status": "closed",
  "source": {
    "trade_log_path": "UPS_py_v2/live/analysis/runs/default/woousdt/5m/linear__cfg_c4d7bc36a9/trade_logs/20260401T080001459339Z.json"
  },
  "signal": {
    "trade_id": "47631422-ceb9-4e36-bfa0-aff416e8f962",
    "logged_at_utc": "2026-04-01T08:00:01.459339+00:00",
    "entry_order_id": "309d5715-e00f-4999-8692-2191a6c7418c",
    "analysis_context": {
      "profile": "default",
      "symbol": "WOOUSDT",
      "timeframe": "5m",
      "category": "linear",
      "config_fingerprint": "c4d7bc36a9",
      "run_dir": "UPS_py_v2/live/analysis/runs/default/woousdt/5m/linear__cfg_c4d7bc36a9"
    },
    "symbol": "WOOUSDT",
    "signal_type": "long",
    "bar_open": 0.017332,
    "bar_high": 0.017377,
    "bar_low": 0.017332,
    "bar_close": 0.017371,
    "bar_volume": 4335.4,
    "bar_atr": 4.674458653401198e-05,
    "price_above_ma": true,
    "long_conditions_met": true,
    "bearish_pb": true,
    "long_entry_pattern": true,
    "intended_entry_price": 0.017371,
    "intended_qty": 1126.2,
    "order_type": "Limit",
    "stop_price": 0.017285255413465987,
    "target_price": 0.017456744586534016,
    "risk_distance": 8.574458653401451e-05,
    "auto_leverage_by_stop": true
  },
  "summary": {
    "entry_order_id": "309d5715-e00f-4999-8692-2191a6c7418c",
    "entry_status": "Filled",
    "entry_created_time_utc": "2026-04-01T08:00:01.556000+00:00",
    "entry_filled_time_utc": "2026-04-01T08:00:01.561000+00:00",
    "entry_avg_price": 0.017371,
    "entry_filled_qty": 1126.2,
    "entry_exec_fee_total": 0.00391265,
    "entry_fee_currencies": [
      "USDT"
    ],
    "exit_order_id": "0699d93e-428b-4aa0-81b9-df74c0c59d35",
    "exit_time_utc": "2026-04-01T08:03:42.502000+00:00",
    "avg_exit_price": 0.017477,
    "closed_pnl": 0.10463912,
    "open_fee": 0.00391265,
    "close_fee": 0.01082543,
    "closed_size": 1126.2,
    "leverage": 18.2
  },
  "matching": {
    "matched_on": "symbol+side+createdTime+qty+avgEntryPrice",
    "time_diff_ms": 379,
    "qty_relative_diff": 0.0,
    "entry_price_relative_diff": 0.0
  },
  "bybit": {
    "entry_order": {
      "symbol": "WOOUSDT",
      "orderType": "Limit",
      "orderLinkId": "47631422-ceb9-4e36-bfa0-aff416e8f962",
      "slLimitPrice": "0",
      "orderId": "309d5715-e00f-4999-8692-2191a6c7418c",
      "cancelType": "UNKNOWN",
      "avgPrice": "0.017371",
      "stopOrderType": "",
      "lastPriceOnCreated": "0.017371",
      "orderStatus": "Filled",
      "createType": "CreateByUser",
      "takeProfit": "",
      "cumExecValue": "19.5632202",
      "tpslMode": "",
      "smpType": "None",
      "triggerDirection": 0,
      "blockTradeId": "",
      "cumFeeDetail": {
        "USDT": "0.00391265"
      },
      "rejectReason": "EC_NoError",
      "isLeverage": "",
      "price": "0.017371",
      "orderIv": "",
      "createdTime": "1775030401556",
      "tpTriggerBy": "",
      "positionIdx": 0,
      "timeInForce": "GTC",
      "leavesValue": "0",
      "updatedTime": "1775030401563",
      "side": "Buy",
      "smpGroup": 0,
      "triggerPrice": "",
      "tpLimitPrice": "0",
      "cumExecFee": "0.00391265",
      "slTriggerBy": "",
      "leavesQty": "0",
      "closeOnTrigger": false,
      "slippageToleranceType": "UNKNOWN",
      "placeType": "",
      "cumExecQty": "1126.2",
      "reduceOnly": false,
      "qty": "1126.2",
      "stopLoss": "",
      "smpOrderId": "",
      "parentOrderLinkId": "",
      "slippageTolerance": "0",
      "triggerBy": "",
      "extraFees": ""
    },
    "entry_executions": [
      {
        "symbol": "WOOUSDT",
        "orderType": "Limit",
        "underlyingPrice": "",
        "orderLinkId": "47631422-ceb9-4e36-bfa0-aff416e8f962",
        "orderId": "309d5715-e00f-4999-8692-2191a6c7418c",
        "stopOrderType": "UNKNOWN",
        "execTime": "1775030401561",
        "feeCurrency": "USDT",
        "createType": "CreateByUser",
        "execFeeV2": "-0.00391265",
        "feeRate": "0.0002",
        "tradeIv": "",
        "blockTradeId": "",
        "markPrice": "0.017371",
        "execPrice": "0.017371",
        "markIv": "",
        "orderQty": "1126.2",
        "orderPrice": "0.017371",
        "execValue": "19.5632202",
        "closedSize": "0",
        "execType": "Trade",
        "seq": 287228636566,
        "side": "Buy",
        "indexPrice": "",
        "leavesQty": "0",
        "isMaker": true,
        "execFee": "0.00391265",
        "execId": "60bc4b17-0dbf-5318-a205-0f0ac69fa09d",
        "marketUnit": "",
        "execQty": "1126.2",
        "extraFees": ""
      }
    ],
    "exit_order": {
      "symbol": "WOOUSDT",
      "orderType": "Limit",
      "orderLinkId": "",
      "slLimitPrice": "0",
      "orderId": "0699d93e-428b-4aa0-81b9-df74c0c59d35",
      "cancelType": "UNKNOWN",
      "avgPrice": "0.017477",
      "stopOrderType": "PartialTakeProfit",
      "lastPriceOnCreated": "0.017475",
      "orderStatus": "Filled",
      "createType": "CreateByPartialTakeProfit",
      "takeProfit": "",
      "cumExecValue": "19.6825974",
      "tpslMode": "Partial",
      "smpType": "None",
      "triggerDirection": 1,
      "blockTradeId": "",
      "cumFeeDetail": {
        "USDT": "0.01082543"
      },
      "rejectReason": "EC_NoError",
      "isLeverage": "",
      "price": "0.017456",
      "orderIv": "",
      "createdTime": "1775030401940",
      "tpTriggerBy": "",
      "positionIdx": 0,
      "timeInForce": "GTC",
      "leavesValue": "0",
      "updatedTime": "1775030622502",
      "side": "Sell",
      "smpGroup": 0,
      "triggerPrice": "0.017456",
      "tpLimitPrice": "0",
      "cumExecFee": "0.01082543",
      "slTriggerBy": "",
      "leavesQty": "0",
      "closeOnTrigger": true,
      "slippageToleranceType": "UNKNOWN",
      "placeType": "",
      "cumExecQty": "1126.2",
      "reduceOnly": true,
      "qty": "1126.2",
      "stopLoss": "",
      "smpOrderId": "",
      "parentOrderLinkId": "",
      "slippageTolerance": "0",
      "triggerBy": "MarkPrice",
      "extraFees": ""
    },
    "exit_executions": [
      {
        "symbol": "WOOUSDT",
        "orderType": "Limit",
        "underlyingPrice": "",
        "orderLinkId": "",
        "orderId": "0699d93e-428b-4aa0-81b9-df74c0c59d35",
        "stopOrderType": "PartialTakeProfit",
        "execTime": "1775030622501",
        "feeCurrency": "USDT",
        "createType": "CreateByPartialTakeProfit",
        "execFeeV2": "-0.01082543",
        "feeRate": "0.00055",
        "tradeIv": "",
        "blockTradeId": "",
        "markPrice": "0.017496",
        "execPrice": "0.017477",
        "markIv": "",
        "orderQty": "1126.2",
        "orderPrice": "0.017456",
        "execValue": "19.6825974",
        "closedSize": "1126.2",
        "execType": "Trade",
        "seq": 287229351546,
        "side": "Sell",
        "indexPrice": "",
        "leavesQty": "0",
        "isMaker": false,
        "execFee": "0.01082543",
        "execId": "af6f460c-f11a-52b3-9a33-0b5026b4aa61",
        "marketUnit": "",
        "execQty": "1126.2",
        "extraFees": ""
      }
    ],
    "closed_pnl": {
      "symbol": "WOOUSDT",
      "orderType": "Limit",
      "leverage": "18.2",
      "updatedTime": "1775030622502",
      "side": "Sell",
      "orderId": "0699d93e-428b-4aa0-81b9-df74c0c59d35",
      "closedPnl": "0.10463912",
      "openFee": "0.00391265",
      "closeFee": "0.01082543",
      "avgEntryPrice": "0.017371",
      "qty": "1126.2",
      "cumEntryValue": "19.5632202",
      "createdTime": "1775030401940",
      "orderPrice": "0.017456",
      "closedSize": "1126.2",
      "avgExitPrice": "0.017477",
      "execType": "Trade",
      "fillCount": "1",
      "cumExitValue": "19.6825974"
    }
  }
}