{
  "trade_id": "b770118b-0c09-4fea-94a8-c22cf88b933d",
  "order_link_id": "b770118b-0c09-4fea-94a8-c22cf88b933d",
  "symbol": "TRXUSDT",
  "signal_type": "long",
  "lifecycle_status": "closed",
  "source": {
    "trade_log_path": "UPS_py_v2/live/analysis/runs/trail_stop_active/trxusdt/5m/linear__cfg_c2f76c59e2/trade_logs/20260328T133501724861Z.json"
  },
  "signal": {
    "trade_id": "b770118b-0c09-4fea-94a8-c22cf88b933d",
    "logged_at_utc": "2026-03-28T13:35:01.724861+00:00",
    "entry_order_id": "28740f13-a47f-4582-9b64-c527d8b8f700",
    "analysis_context": {
      "profile": "trail_stop_active",
      "symbol": "TRXUSDT",
      "timeframe": "5m",
      "category": "linear",
      "config_fingerprint": "c2f76c59e2",
      "run_dir": "UPS_py_v2/live/analysis/runs/trail_stop_active/trxusdt/5m/linear__cfg_c2f76c59e2"
    },
    "symbol": "TRXUSDT",
    "signal_type": "long",
    "bar_open": 0.3147,
    "bar_high": 0.3151,
    "bar_low": 0.31455,
    "bar_close": 0.3151,
    "bar_volume": 118817.0,
    "bar_atr": 0.0004975457445537252,
    "price_above_ma": true,
    "long_conditions_met": true,
    "bearish_pb": true,
    "long_entry_pattern": true,
    "intended_entry_price": 0.3151,
    "intended_qty": 94.0,
    "order_type": "Limit",
    "stop_price": 0.31395245425544627,
    "target_price": 0.3162475457445537,
    "risk_distance": 0.001147545744553724,
    "auto_leverage_by_stop": true
  },
  "summary": {
    "entry_order_id": "28740f13-a47f-4582-9b64-c527d8b8f700",
    "entry_status": "Filled",
    "entry_created_time_utc": "2026-03-28T13:35:01.836000+00:00",
    "entry_filled_time_utc": "2026-03-28T13:35:01.837000+00:00",
    "entry_avg_price": 0.31507,
    "entry_filled_qty": 94.0,
    "entry_exec_fee_total": 0.01628912,
    "entry_fee_currencies": [
      "USDT"
    ],
    "exit_order_id": "81a2b9d9-5b83-498d-ae0b-7984c90c01f3",
    "exit_time_utc": "2026-03-28T15:26:32.560000+00:00",
    "avg_exit_price": 0.3155,
    "closed_pnl": 0.00781953,
    "open_fee": 0.01628912,
    "close_fee": 0.01631135,
    "closed_size": 94.0,
    "leverage": 10.0
  },
  "matching": {
    "matched_on": "symbol+side+createdTime+qty+avgEntryPrice",
    "time_diff_ms": 584,
    "qty_relative_diff": 0.0,
    "entry_price_relative_diff": 0.0
  },
  "bybit": {
    "entry_order": {
      "symbol": "TRXUSDT",
      "orderType": "Limit",
      "orderLinkId": "b770118b-0c09-4fea-94a8-c22cf88b933d",
      "slLimitPrice": "0",
      "orderId": "28740f13-a47f-4582-9b64-c527d8b8f700",
      "cancelType": "UNKNOWN",
      "avgPrice": "0.31507",
      "stopOrderType": "",
      "lastPriceOnCreated": "0.3151",
      "orderStatus": "Filled",
      "createType": "CreateByUser",
      "takeProfit": "",
      "cumExecValue": "29.61658",
      "tpslMode": "",
      "smpType": "None",
      "triggerDirection": 0,
      "blockTradeId": "",
      "cumFeeDetail": {
        "USDT": "0.01628912"
      },
      "rejectReason": "EC_NoError",
      "isLeverage": "",
      "price": "0.3151",
      "orderIv": "",
      "createdTime": "1774704901836",
      "tpTriggerBy": "",
      "positionIdx": 0,
      "timeInForce": "GTC",
      "leavesValue": "0",
      "updatedTime": "1774704901839",
      "side": "Buy",
      "smpGroup": 0,
      "triggerPrice": "",
      "tpLimitPrice": "0",
      "cumExecFee": "0.01628912",
      "slTriggerBy": "",
      "leavesQty": "0",
      "closeOnTrigger": false,
      "slippageToleranceType": "UNKNOWN",
      "placeType": "",
      "cumExecQty": "94",
      "reduceOnly": false,
      "qty": "94",
      "stopLoss": "",
      "smpOrderId": "",
      "parentOrderLinkId": "",
      "slippageTolerance": "0",
      "triggerBy": "",
      "extraFees": ""
    },
    "entry_executions": [
      {
        "symbol": "TRXUSDT",
        "orderType": "Limit",
        "underlyingPrice": "",
        "orderLinkId": "b770118b-0c09-4fea-94a8-c22cf88b933d",
        "orderId": "28740f13-a47f-4582-9b64-c527d8b8f700",
        "stopOrderType": "UNKNOWN",
        "execTime": "1774704901837",
        "feeCurrency": "USDT",
        "createType": "CreateByUser",
        "execFeeV2": "-0.01628912",
        "feeRate": "0.00055",
        "tradeIv": "",
        "blockTradeId": "",
        "markPrice": "0.31504",
        "execPrice": "0.31507",
        "markIv": "",
        "orderQty": "94",
        "orderPrice": "0.3151",
        "execValue": "29.61658",
        "closedSize": "0",
        "execType": "Trade",
        "seq": 286253404552,
        "side": "Buy",
        "indexPrice": "",
        "leavesQty": "0",
        "isMaker": false,
        "execFee": "0.01628912",
        "execId": "b64f8e08-aa31-5d83-ae20-a503a846c344",
        "marketUnit": "",
        "execQty": "94",
        "extraFees": ""
      }
    ],
    "exit_order": {
      "symbol": "TRXUSDT",
      "orderType": "Market",
      "orderLinkId": "",
      "slLimitPrice": "0",
      "orderId": "81a2b9d9-5b83-498d-ae0b-7984c90c01f3",
      "cancelType": "UNKNOWN",
      "avgPrice": "0.3155",
      "stopOrderType": "StopLoss",
      "lastPriceOnCreated": "0.3155",
      "orderStatus": "Filled",
      "createType": "CreateByStopLoss",
      "takeProfit": "",
      "cumExecValue": "29.657",
      "tpslMode": "Full",
      "smpType": "None",
      "triggerDirection": 2,
      "blockTradeId": "",
      "cumFeeDetail": {
        "USDT": "0.01631135"
      },
      "rejectReason": "EC_NoError",
      "isLeverage": "",
      "price": "0.29973",
      "orderIv": "",
      "createdTime": "1774704902421",
      "tpTriggerBy": "",
      "positionIdx": 0,
      "timeInForce": "IOC",
      "leavesValue": "0",
      "updatedTime": "1774711592560",
      "side": "Sell",
      "smpGroup": 0,
      "triggerPrice": "0.3155",
      "tpLimitPrice": "0",
      "cumExecFee": "0.01631135",
      "slTriggerBy": "",
      "leavesQty": "0",
      "closeOnTrigger": true,
      "slippageToleranceType": "UNKNOWN",
      "placeType": "",
      "cumExecQty": "94",
      "reduceOnly": true,
      "qty": "94",
      "stopLoss": "",
      "smpOrderId": "",
      "parentOrderLinkId": "",
      "slippageTolerance": "0",
      "triggerBy": "MarkPrice",
      "extraFees": ""
    },
    "exit_executions": [
      {
        "symbol": "TRXUSDT",
        "orderType": "Market",
        "underlyingPrice": "",
        "orderLinkId": "",
        "orderId": "81a2b9d9-5b83-498d-ae0b-7984c90c01f3",
        "stopOrderType": "StopLoss",
        "execTime": "1774711592558",
        "feeCurrency": "USDT",
        "createType": "CreateByStopLoss",
        "execFeeV2": "-0.01631135",
        "feeRate": "0.00055",
        "tradeIv": "",
        "blockTradeId": "",
        "markPrice": "0.3155",
        "execPrice": "0.3155",
        "markIv": "",
        "orderQty": "94",
        "orderPrice": "0.29973",
        "execValue": "29.657",
        "closedSize": "94",
        "execType": "Trade",
        "seq": 286282928859,
        "side": "Sell",
        "indexPrice": "",
        "leavesQty": "0",
        "isMaker": false,
        "execFee": "0.01631135",
        "execId": "756d88dd-9831-504e-8b82-d6d4b73f592e",
        "marketUnit": "",
        "execQty": "94",
        "extraFees": ""
      }
    ],
    "closed_pnl": {
      "symbol": "TRXUSDT",
      "orderType": "Market",
      "leverage": "10",
      "updatedTime": "1774711592560",
      "side": "Sell",
      "orderId": "81a2b9d9-5b83-498d-ae0b-7984c90c01f3",
      "closedPnl": "0.00781953",
      "openFee": "0.01628912",
      "closeFee": "0.01631135",
      "avgEntryPrice": "0.31507",
      "qty": "94",
      "cumEntryValue": "29.61658",
      "createdTime": "1774704902421",
      "orderPrice": "0.29973",
      "closedSize": "94",
      "avgExitPrice": "0.3155",
      "execType": "Trade",
      "fillCount": "1",
      "cumExitValue": "29.657"
    }
  }
}